rebootpy/__init__.py
rebootpy/auth.py
rebootpy/avatar.py
rebootpy/client.py
rebootpy/creative.py
rebootpy/enums.py
rebootpy/errors.py
rebootpy/friend.py
rebootpy/http.py
rebootpy/message.py
rebootpy/news.py
rebootpy/party.py
rebootpy/playlist.py
rebootpy/presence.py
rebootpy/stats.py
rebootpy/store.py
rebootpy/typedefs.py
rebootpy/user.py
rebootpy/utils.py
rebootpy/websocket.py
rebootpy/xmpp.py
rebootpy/ext/commands/__init__.py
rebootpy/ext/commands/_types.py
rebootpy/ext/commands/bot.py
rebootpy/ext/commands/cog.py
rebootpy/ext/commands/context.py
rebootpy/ext/commands/converter.py
rebootpy/ext/commands/cooldown.py
rebootpy/ext/commands/core.py
rebootpy/ext/commands/errors.py
rebootpy/ext/commands/help.py
rebootpy/ext/commands/typedefs.py
rebootpy/ext/commands/view.py
rebootpy-0.9.5.dist-info/licenses/LICENSE
rebootpy-0.9.5.dist-info/METADATA
rebootpy-0.9.5.dist-info/WHEEL
rebootpy-0.9.5.dist-info/top_level.txt
rebootpy-0.9.5.dist-info/RECORD
