Metadata-Version: 2.4
Name: rebootpy
Version: 0.9.5
Summary: Library for interacting with fortnite services
Home-page: https://github.com/xMistt/rebootpy
Author: xMistt
License: MIT
Project-URL: Documentation, https://rebootpy.readthedocs.io/en/latest/
Project-URL: Issue tracker, https://github.com/xMistt/rebootpy/issues
Classifier: License :: OSI Approved :: MIT License
Classifier: Intended Audience :: Developers
Classifier: Natural Language :: English
Classifier: Operating System :: OS Independent
Classifier: Programming Language :: Python :: 3.7
Classifier: Programming Language :: Python :: 3.8
Classifier: Programming Language :: Python :: 3.9
Classifier: Programming Language :: Python :: 3.10
Classifier: Programming Language :: Python :: 3.11
Classifier: Programming Language :: Python :: 3.12
Classifier: Topic :: Internet
Classifier: Topic :: Software Development :: Libraries
Classifier: Topic :: Software Development :: Libraries :: Python Modules
Classifier: Topic :: Utilities
Requires-Python: >=3.7.0
License-File: LICENSE
Requires-Dist: aiohttp>=3.10.10
Requires-Dist: aioxmpp>=0.13.3
Requires-Dist: aioconsole>=0.1.15
Requires-Dist: pytz>=2024.2
Provides-Extra: docs
Requires-Dist: sphinxcontrib_trio==1.1.2; extra == "docs"
Requires-Dist: furo==2021.4.11b34; extra == "docs"
Requires-Dist: Jinja2<3.1; extra == "docs"
Dynamic: author
Dynamic: classifier
Dynamic: description
Dynamic: description-content-type
Dynamic: home-page
Dynamic: license
Dynamic: license-file
Dynamic: project-url
Dynamic: provides-extra
Dynamic: requires-dist
Dynamic: requires-python
Dynamic: summary
